pysisoulnfc/__init__.py
pysisoulnfc/device.py
pysisoulnfc/nfc.py
SisoulNfc-0.6.0.dist-info/METADATA
SisoulNfc-0.6.0.dist-info/WHEEL
SisoulNfc-0.6.0.dist-info/top_level.txt
SisoulNfc-0.6.0.dist-info/RECORD
