Metadata-Version: 2.1
Name: SisoulNfc
Version: 0.6.0
Summary: Sisoul NFC SDK for SMCP-IV
Home-page: http://sisoul.co.kr
Author: Kim Youngseon
Author-email: sean.kim@sisoul.co.kr
License: Commercial
Keywords: nfc
Platform: UNKNOWN
Classifier: Programming Language :: Python :: 3
Classifier: Programming Language :: Python :: 3.5
Classifier: Programming Language :: Python :: 3.6
Requires-Python: >=3.5
Requires-Dist: Cython
Requires-Dist: hidapi
Requires-Dist: pyftdi
Requires-Dist: multipledispatch
